{
  "aor": 0.0023865853658536582,
  "aqi": 0.005533345182926829,
  "bids_meta": {
    "dataset": "ds000241",
    "modality": "bold",
    "run_id": 6,
    "subject_id": "01",
    "task_id": "ak6"
  },
  "dummy_trs": 0,
  "dvars_nstd": 24.396836707852756,
  "dvars_std": 1.3658168125766863,
  "dvars_vstd": 1.009516919018405,
  "efc": 0.3948180164334164,
  "fber": 108945.7734375,
  "fd_mean": 0.08788655201097775,
  "fd_num": 5,
  "fd_perc": 3.048780487804878,
  "fwhm_avg": 1.9642955555555555,
  "fwhm_x": 1.8444366666666667,
  "fwhm_y": 2.2121299999999997,
  "fwhm_z": 1.83632,
  "gcor": 0.022833,
  "gsr_x": -0.007507719565182924,
  "gsr_y": 0.009984264150261879,
  "provenance": {
    "md5sum": "d8efbee7ecd7061332a4f35bf0002acf",
    "settings": {
      "fd_thres": 0.2,
      "testing": false
    },
    "software": "mriqc",
    "version": "22.0.1",
    "webapi_port": null,
    "webapi_url": "https://mriqc.nimh.nih.gov/api/v1"
  },
  "size_t": 164,
  "size_x": 80,
  "size_y": 80,
  "size_z": 43,
  "snr": 6.108807691967166,
  "spacing_tr": 2.0,
  "spacing_x": 3.0,
  "spacing_y": 3.0,
  "spacing_z": 3.0,
  "summary_bg_k": 45.91947177130404,
  "summary_bg_mad": 3881.881076604916,
  "summary_bg_mean": 16754.15625,
  "summary_bg_median": 2677.130615234375,
  "summary_bg_n": 197229.0,
  "summary_bg_p05": 16.72219314575195,
  "summary_bg_p95": 87252.59062499987,
  "summary_bg_stdv": 46606.74609375,
  "summary_fg_k": 1.3590002586469314,
  "summary_fg_mad": 117854.13525838008,
  "summary_fg_mean": 826539.8125,
  "summary_fg_median": 815913.5,
  "summary_fg_n": 35170.0,
  "summary_fg_p05": 638105.384375,
  "summary_fg_p95": 1069945.1062499997,
  "summary_fg_stdv": 133561.5625,
  "tsnr": 77.2537841796875
}